{
  "30": {
    "name": "Cyprus",
    "groups": [
      "Developing countries",
      "Europe"
    ]
  },
  "35": {
    "name": "Gibraltar",
    "groups": [
      "Developing countries",
      "Europe"
    ]
  },
  "45": {
    "name": "Malta",
    "groups": [
      "Developing countries",
      "Europe"
    ]
  },
  "55": {
    "name": "Turkey",
    "groups": [
      "Developing countries",
      "Europe",
      "Upper-middle income countries",
      "Middle income countries"
    ]
  },
  "57": {
    "name": "Kosovo",
    "groups": [
      "Developing countries",
      "Europe",
      "Upper-middle income countries",
      "Middle income countries"
    ]
  },
  "61": {
    "name": "Slovenia",
    "groups": [
      "Developing countries",
      "Europe"
    ]
  },
  "62": {
    "name": "Croatia",
    "groups": [
      "Developing countries",
      "Europe"
    ]
  },
  "63": {
    "name": "Serbia",
    "groups": [
      "Developing countries",
      "Europe",
      "Upper-middle income countries",
      "Middle income countries"
    ]
  },
  "64": {
    "name": "Bosnia and Herzegovina",
    "groups": [
      "Developing countries",
      "Europe",
      "Upper-middle income countries",
      "Middle income countries"
    ]
  },
  "65": {
    "name": "Montenegro",
    "groups": [
      "Developing countries",
      "Europe",
      "Upper-middle income countries",
      "Middle income countries"
    ]
  },
  "66": {
    "name": "North Macedonia",
    "groups": [
      "Developing countries",
      "Europe",
      "Upper-middle income countries",
      "Middle income countries"
    ]
  },
  "71": {
    "name": "Albania",
    "groups": [
      "Developing countries",
      "Europe",
      "Upper-middle income countries",
      "Middle income countries"
    ]
  },
  "85": {
    "name": "Ukraine",
    "groups": [
      "Developing countries",
      "Europe",
      "Lower-middle income countries",
      "Middle income countries"
    ]
  },
  "86": {
    "name": "Belarus",
    "groups": [
      "Developing countries",
      "Europe",
      "Upper-middle income countries",
      "Middle income countries"
    ]
  },
  "89": {
    "name": "Europe, unspecified",
    "groups": [
      "Developing countries",
      "Europe"
    ]
  },
  "93": {
    "name": "Moldova",
    "groups": [
      "Developing countries",
      "Europe",
      "Upper-middle income countries",
      "Middle income countries"
    ]
  },
  "130": {
    "name": "Algeria",
    "groups": [
      "Developing countries",
      "Africa",
      "Northern Africa",
      "Lower-middle income countries",
      "Middle income countries"
    ]
  },
  "133": {
    "name": "Libya",
    "groups": [
      "Developing countries",
      "Africa",
      "Northern Africa",
      "Upper-middle income countries",
      "Middle income countries"
    ]
  },
  "136": {
    "name": "Morocco",
    "groups": [
      "Developing countries",
      "Africa",
      "Northern Africa",
      "Lower-middle income countries",
      "Middle income countries"
    ]
  },
  "139": {
    "name": "Tunisia",
    "groups": [
      "Developing countries",
      "Africa",
      "Northern Africa",
      "Lower-middle income countries",
      "Middle income countries"
    ]
  },
  "142": {
    "name": "Egypt",
    "groups": [
      "Developing countries",
      "Africa",
      "Northern Africa",
      "Lower-middle income countries",
      "Middle income countries"
    ]
  },
  "189": {
    "name": "Northern Africa, unspecified",
    "groups": [
      "Developing countries",
      "Africa",
      "Northern Africa"
    ]
  },
  "218": {
    "name": "South Africa",
    "groups": [
      "Developing countries",
      "Africa",
      "Sub-Saharan Africa",
      "Southern Africa",
      "Upper-middle income countries",
      "Middle income countries"
    ]
  },
  "225": {
    "name": "Angola",
    "groups": [
      "Developing countries",
      "Africa",
      "Sub-Saharan Africa",
      "Middle Africa",
      "Least developed countries",
      "Fragile and conflict-affected countries"
    ]
  },
  "227": {
    "name": "Botswana",
    "groups": [
      "Developing countries",
      "Africa",
      "Sub-Saharan Africa",
      "Southern Africa",
      "Upper-middle income countries",
      "Middle income countries"
    ]
  },
  "228": {
    "name": "Burundi",
    "groups": [
      "Developing countries",
      "Africa",
      "Sub-Saharan Africa",
      "Eastern Africa",
      "France priority countries",
      "Least developed countries",
      "Fragile and conflict-affected countries"
    ]
  },
  "229": {
    "name": "Cameroon",
    "groups": [
      "Developing countries",
      "Africa",
      "Sub-Saharan Africa",
      "Middle Africa",
      "Lower-middle income countries",
      "Middle income countries",
      "Fragile and conflict-affected countries"
    ]
  },
  "230": {
    "name": "Cabo Verde",
    "groups": [
      "Developing countries",
      "Africa",
      "Sub-Saharan Africa",
      "Western Africa",
      "Lower-middle income countries",
      "Middle income countries"
    ]
  },
  "231": {
    "name": "Central African Republic",
    "groups": [
      "Developing countries",
      "Africa",
      "Sub-Saharan Africa",
      "Middle Africa",
      "France priority countries",
      "Least developed countries",
      "Fragile and conflict-affected countries"
    ]
  },
  "232": {
    "name": "Chad",
    "groups": [
      "Developing countries",
      "Africa",
      "Sub-Saharan Africa",
      "Middle Africa",
      "France priority countries",
      "Least developed countries",
      "Sahel countries",
      "Fragile and conflict-affected countries"
    ]
  },
  "233": {
    "name": "Comoros",
    "groups": [
      "Developing countries",
      "Africa",
      "Sub-Saharan Africa",
      "Eastern Africa",
      "France priority countries",
      "Least developed countries",
      "Fragile and conflict-affected countries"
    ]
  },
  "234": {
    "name": "Congo",
    "groups": [
      "Developing countries",
      "Africa",
      "Sub-Saharan Africa",
      "Middle Africa",
      "Lower-middle income countries",
      "Middle income countries",
      "Fragile and conflict-affected countries"
    ]
  },
  "235": {
    "name": "Democratic Republic of the Congo",
    "groups": [
      "Developing countries",
      "Africa",
      "Sub-Saharan Africa",
      "Middle Africa",
      "France priority countries",
      "Least developed countries",
      "Fragile and conflict-affected countries"
    ]
  },
  "236": {
    "name": "Benin",
    "groups": [
      "Developing countries",
      "Africa",
      "Sub-Saharan Africa",
      "Western Africa",
      "France priority countries",
      "Least developed countries",
      "Fragile and conflict-affected countries"
    ]
  },
  "238": {
    "name": "Ethiopia",
    "groups": [
      "Developing countries",
      "Africa",
      "Sub-Saharan Africa",
      "Eastern Africa",
      "France priority countries",
      "Least developed countries",
      "Fragile and conflict-affected countries"
    ]
  },
  "239": {
    "name": "Gabon",
    "groups": [
      "Developing countries",
      "Africa",
      "Sub-Saharan Africa",
      "Middle Africa",
      "Upper-middle income countries",
      "Middle income countries"
    ]
  },
  "240": {
    "name": "Gambia",
    "groups": [
      "Developing countries",
      "Africa",
      "Sub-Saharan Africa",
      "Western Africa",
      "France priority countries",
      "Least developed countries",
      "Fragile and conflict-affected countries"
    ]
  },
  "241": {
    "name": "Ghana",
    "groups": [
      "Developing countries",
      "Africa",
      "Sub-Saharan Africa",
      "Western Africa",
      "Lower-middle income countries",
      "Middle income countries"
    ]
  },
  "243": {
    "name": "Guinea",
    "groups": [
      "Developing countries",
      "Africa",
      "Sub-Saharan Africa",
      "Western Africa",
      "France priority countries",
      "Least developed countries"
    ]
  },
  "244": {
    "name": "Guinea-Bissau",
    "groups": [
      "Developing countries",
      "Africa",
      "Sub-Saharan Africa",
      "Western Africa",
      "Least developed countries",
      "Fragile and conflict-affected countries"
    ]
  },
  "245": {
    "name": "Equatorial Guinea",
    "groups": [
      "Developing countries",
      "Africa",
      "Sub-Saharan Africa",
      "Middle Africa",
      "Upper-middle income countries",
      "Middle income countries",
      "Fragile and conflict-affected countries"
    ]
  },
  "247": {
    "name": "Cote d'Ivoire",
    "groups": [
      "Developing countries",
      "Africa",
      "Sub-Saharan Africa",
      "Western Africa",
      "Lower-middle income countries",
      "Middle income countries",
      "Fragile and conflict-affected countries"
    ]
  },
  "248": {
    "name": "Kenya",
    "groups": [
      "Developing countries",
      "Africa",
      "Sub-Saharan Africa",
      "Eastern Africa",
      "Lower-middle income countries",
      "Middle income countries",
      "Fragile and conflict-affected countries"
    ]
  },
  "249": {
    "name": "Lesotho",
    "groups": [
      "Developing countries",
      "Africa",
      "Sub-Saharan Africa",
      "Southern Africa",
      "Least developed countries",
      "Fragile and conflict-affected countries"
    ]
  },
  "251": {
    "name": "Liberia",
    "groups": [
      "Developing countries",
      "Africa",
      "Sub-Saharan Africa",
      "Western Africa",
      "France priority countries",
      "Least developed countries",
      "Fragile and conflict-affected countries"
    ]
  },
  "252": {
    "name": "Madagascar",
    "groups": [
      "Developing countries",
      "Africa",
      "Sub-Saharan Africa",
      "Eastern Africa",
      "France priority countries",
      "Least developed countries",
      "Fragile and conflict-affected countries"
    ]
  },
  "253": {
    "name": "Malawi",
    "groups": [
      "Developing countries",
      "Africa",
      "Sub-Saharan Africa",
      "Eastern Africa",
      "Least developed countries"
    ]
  },
  "255": {
    "name": "Mali",
    "groups": [
      "Developing countries",
      "Africa",
      "Sub-Saharan Africa",
      "Western Africa",
      "France priority countries",
      "Least developed countries",
      "Sahel countries",
      "Fragile and conflict-affected countries"
    ]
  },
  "256": {
    "name": "Mauritania",
    "groups": [
      "Developing countries",
      "Africa",
      "Sub-Saharan Africa",
      "Western Africa",
      "France priority countries",
      "Least developed countries",
      "Sahel countries",
      "Fragile and conflict-affected countries"
    ]
  },
  "257": {
    "name": "Mauritius",
    "groups": [
      "Developing countries",
      "Africa",
      "Sub-Saharan Africa",
      "Eastern Africa",
      "Upper-middle income countries",
      "Middle income countries"
    ]
  },
  "258": {
    "name": "Mayotte",
    "groups": [
      "Developing countries",
      "Africa",
      "Sub-Saharan Africa",
      "Eastern Africa"
    ]
  },
  "259": {
    "name": "Mozambique",
    "groups": [
      "Developing countries",
      "Africa",
      "Sub-Saharan Africa",
      "Eastern Africa",
      "Least developed countries",
      "Fragile and conflict-affected countries"
    ]
  },
  "260": {
    "name": "Niger",
    "groups": [
      "Developing countries",
      "Africa",
      "Sub-Saharan Africa",
      "Western Africa",
      "France priority countries",
      "Least developed countries",
      "Sahel countries",
      "Fragile and conflict-affected countries"
    ]
  },
  "261": {
    "name": "Nigeria",
    "groups": [
      "Developing countries",
      "Africa",
      "Sub-Saharan Africa",
      "Western Africa",
      "Lower-middle income countries",
      "Middle income countries",
      "Fragile and conflict-affected countries"
    ]
  },
  "265": {
    "name": "Zimbabwe",
    "groups": [
      "Developing countries",
      "Africa",
      "Sub-Saharan Africa",
      "Eastern Africa",
      "Lower-middle income countries",
      "Middle income countries",
      "Fragile and conflict-affected countries"
    ]
  },
  "266": {
    "name": "Rwanda",
    "groups": [
      "Developing countries",
      "Africa",
      "Sub-Saharan Africa",
      "Eastern Africa",
      "Least developed countries"
    ]
  },
  "268": {
    "name": "Sao Tome and Principe",
    "groups": [
      "Developing countries",
      "Africa",
      "Sub-Saharan Africa",
      "Middle Africa",
      "Least developed countries"
    ]
  },
  "269": {
    "name": "Senegal",
    "groups": [
      "Developing countries",
      "Africa",
      "Sub-Saharan Africa",
      "Western Africa",
      "France priority countries",
      "Least developed countries"
    ]
  },
  "270": {
    "name": "Seychelles",
    "groups": [
      "Developing countries",
      "Africa",
      "Sub-Saharan Africa",
      "Eastern Africa"
    ]
  },
  "271": {
    "name": "Eritrea",
    "groups": [
      "Developing countries",
      "Africa",
      "Sub-Saharan Africa",
      "Eastern Africa",
      "Least developed countries",
      "Fragile and conflict-affected countries"
    ]
  },
  "272": {
    "name": "Sierra Leone",
    "groups": [
      "Developing countries",
      "Africa",
      "Sub-Saharan Africa",
      "Western Africa",
      "Least developed countries",
      "Fragile and conflict-affected countries"
    ]
  },
  "273": {
    "name": "Somalia",
    "groups": [
      "Developing countries",
      "Africa",
      "Sub-Saharan Africa",
      "Eastern Africa",
      "Least developed countries",
      "Fragile and conflict-affected countries"
    ]
  },
  "274": {
    "name": "Djibouti",
    "groups": [
      "Developing countries",
      "Africa",
      "Sub-Saharan Africa",
      "Eastern Africa",
      "France priority countries",
      "Least developed countries",
      "Fragile and conflict-affected countries"
    ]
  },
  "275": {
    "name": "Namibia",
    "groups": [
      "Developing countries",
      "Africa",
      "Sub-Saharan Africa",
      "Southern Africa",
      "Upper-middle income countries",
      "Middle income countries"
    ]
  },
  "276": {
    "name": "Saint Helena",
    "groups": [
      "Developing countries",
      "Africa",
      "Sub-Saharan Africa",
      "Western Africa",
      "Upper-middle income countries",
      "Middle income countries"
    ]
  },
  "278": {
    "name": "Sudan",
    "groups": [
      "Developing countries",
      "Africa",
      "Sub-Saharan Africa",
      "Eastern Africa",
      "Least developed countries"
    ]
  },
  "279": {
    "name": "South Sudan",
    "groups": [
      "Developing countries",
      "Africa",
      "Sub-Saharan Africa",
      "Eastern Africa",
      "Least developed countries",
      "Fragile and conflict-affected countries"
    ]
  },
  "280": {
    "name": "Eswatini",
    "groups": [
      "Developing countries",
      "Africa",
      "Sub-Saharan Africa",
      "Southern Africa",
      "Lower-middle income countries",
      "Middle income countries",
      "Fragile and conflict-affected countries"
    ]
  },
  "282": {
    "name": "Tanzania",
    "groups": [
      "Developing countries",
      "Africa",
      "Sub-Saharan Africa",
      "Eastern Africa",
      "Least developed countries",
      "Fragile and conflict-affected countries"
    ]
  },
  "283": {
    "name": "Togo",
    "groups": [
      "Developing countries",
      "Africa",
      "Sub-Saharan Africa",
      "Western Africa",
      "France priority countries",
      "Least developed countries",
      "Fragile and conflict-affected countries"
    ]
  },
  "285": {
    "name": "Uganda",
    "groups": [
      "Developing countries",
      "Africa",
      "Sub-Saharan Africa",
      "Eastern Africa",
      "Least developed countries",
      "Fragile and conflict-affected countries"
    ]
  },
  "287": {
    "name": "Burkina Faso",
    "groups": [
      "Developing countries",
      "Africa",
      "Sub-Saharan Africa",
      "Western Africa",
      "France priority countries",
      "Least developed countries",
      "Sahel countries",
      "Fragile and conflict-affected countries"
    ]
  },
  "288": {
    "name": "Zambia",
    "groups": [
      "Developing countries",
      "Africa",
      "Sub-Saharan Africa",
      "Eastern Africa",
      "Least developed countries",
      "Fragile and conflict-affected countries"
    ]
  },
  "289": {
    "name": "Sub-Saharan Africa, unspecified",
    "groups": [
      "Developing countries",
      "Africa",
      "Sub-Saharan Africa"
    ]
  },
  "298": {
    "name": "Africa, unspecified",
    "groups": [
      "Developing countries",
      "Africa"
    ]
  },
  "328": {
    "name": "Bahamas",
    "groups": [
      "Developing countries",
      "America",
      "Central America and the Caribbean",
      "Caribbean"
    ]
  },
  "329": {
    "name": "Barbados",
    "groups": [
      "Developing countries",
      "America",
      "Central America and the Caribbean",
      "Caribbean"
    ]
  },
  "331": {
    "name": "Bermuda",
    "groups": [
      "Developing countries",
      "America",
      "North America"
    ]
  },
  "336": {
    "name": "Costa Rica",
    "groups": [
      "Developing countries",
      "America",
      "Central America and the Caribbean",
      "Central America",
      "Upper-middle income countries",
      "Middle income countries"
    ]
  },
  "338": {
    "name": "Cuba",
    "groups": [
      "Developing countries",
      "America",
      "Central America and the Caribbean",
      "Caribbean",
      "Upper-middle income countries",
      "Middle income countries"
    ]
  },
  "340": {
    "name": "Dominican Republic",
    "groups": [
      "Developing countries",
      "America",
      "Central America and the Caribbean",
      "Caribbean",
      "Upper-middle income countries",
      "Middle income countries"
    ]
  },
  "342": {
    "name": "El Salvador",
    "groups": [
      "Developing countries",
      "America",
      "Central America and the Caribbean",
      "Central America",
      "Lower-middle income countries",
      "Middle income countries"
    ]
  },
  "347": {
    "name": "Guatemala",
    "groups": [
      "Developing countries",
      "America",
      "Central America and the Caribbean",
      "Central America",
      "Upper-middle income countries",
      "Middle income countries"
    ]
  },
  "349": {
    "name": "Haiti",
    "groups": [
      "Developing countries",
      "America",
      "Central America and the Caribbean",
      "Caribbean",
      "France priority countries",
      "Least developed countries",
      "Fragile and conflict-affected countries"
    ]
  },
  "351": {
    "name": "Honduras",
    "groups": [
      "Developing countries",
      "America",
      "Central America and the Caribbean",
      "Central America",
      "Lower-middle income countries",
      "Middle income countries",
      "Fragile and conflict-affected countries"
    ]
  },
  "352": {
    "name": "Belize",
    "groups": [
      "Developing countries",
      "America",
      "Central America and the Caribbean",
      "Central America",
      "Lower-middle income countries",
      "Middle income countries"
    ]
  },
  "354": {
    "name": "Jamaica",
    "groups": [
      "Developing countries",
      "America",
      "Central America and the Caribbean",
      "Caribbean",
      "Upper-middle income countries",
      "Middle income countries"
    ]
  },
  "358": {
    "name": "Mexico",
    "groups": [
      "Developing countries",
      "America",
      "Central America and the Caribbean",
      "Central America",
      "Upper-middle income countries",
      "Middle income countries"
    ]
  },
  "364": {
    "name": "Nicaragua",
    "groups": [
      "Developing countries",
      "America",
      "Central America and the Caribbean",
      "Central America",
      "Lower-middle income countries",
      "Middle income countries",
      "Fragile and conflict-affected countries"
    ]
  },
  "366": {
    "name": "Panama",
    "groups": [
      "Developing countries",
      "America",
      "Central America and the Caribbean",
      "Central America",
      "Upper-middle income countries",
      "Middle income countries"
    ]
  },
  "373": {
    "name": "Aruba",
    "groups": [
      "Developing countries",
      "America",
      "Central America and the Caribbean",
      "Caribbean"
    ]
  },
  "375": {
    "name": "Trinidad and Tobago",
    "groups": [
      "Developing countries",
      "America",
      "Central America and the Caribbean",
      "Caribbean"
    ]
  },
  "376": {
    "name": "Anguilla",
    "groups": [
      "Developing countries",
      "America",
      "Central America and the Caribbean",
      "Caribbean"
    ]
  },
  "377": {
    "name": "Antigua and Barbuda",
    "groups": [
      "Developing countries",
      "America",
      "Central America and the Caribbean",
      "Caribbean"
    ]
  },
  "378": {
    "name": "Dominica",
    "groups": [
      "Developing countries",
      "America",
      "Central America and the Caribbean",
      "Caribbean",
      "Upper-middle income countries",
      "Middle income countries"
    ]
  },
  "381": {
    "name": "Grenada",
    "groups": [
      "Developing countries",
      "America",
      "Central America and the Caribbean",
      "Caribbean",
      "Upper-middle income countries",
      "Middle income countries"
    ]
  },
  "382": {
    "name": "Saint Kitts and Nevis",
    "groups": [
      "Developing countries",
      "America",
      "Central America and the Caribbean",
      "Caribbean"
    ]
  },
  "383": {
    "name": "Saint Lucia",
    "groups": [
      "Developing countries",
      "America",
      "Central America and the Caribbean",
      "Caribbean",
      "Upper-middle income countries",
      "Middle income countries"
    ]
  },
  "384": {
    "name": "Saint Vincent and the Grenadines",
    "groups": [
      "Developing countries",
      "America",
      "Central America and the Caribbean",
      "Caribbean",
      "Upper-middle income countries",
      "Middle income countries"
    ]
  },
  "385": {
    "name": "Montserrat",
    "groups": [
      "Developing countries",
      "America",
      "Central America and the Caribbean",
      "Caribbean",
      "Upper-middle income countries",
      "Middle income countries"
    ]
  },
  "386": {
    "name": "Cayman Islands",
    "groups": [
      "Developing countries",
      "America",
      "Central America and the Caribbean",
      "Caribbean"
    ]
  },
  "387": {
    "name": "Turks and Caicos Islands",
    "groups": [
      "Developing countries",
      "America",
      "Central America and the Caribbean",
      "Caribbean"
    ]
  },
  "388": {
    "name": "British Virgin Islands",
    "groups": [
      "Developing countries",
      "America",
      "Central America and the Caribbean",
      "Caribbean"
    ]
  },
  "389": {
    "name": "Central America and the Caribbean, unspecified",
    "groups": [
      "Developing countries",
      "America",
      "Central America and the Caribbean"
    ]
  },
  "425": {
    "name": "Argentina",
    "groups": [
      "Developing countries",
      "America",
      "South America",
      "Upper-middle income countries",
      "Middle income countries"
    ]
  },
  "428": {
    "name": "Bolivia",
    "groups": [
      "Developing countries",
      "America",
      "South America",
      "Lower-middle income countries",
      "Middle income countries"
    ]
  },
  "431": {
    "name": "Brazil",
    "groups": [
      "Developing countries",
      "America",
      "South America",
      "Upper-middle income countries",
      "Middle income countries"
    ]
  },
  "434": {
    "name": "Chile",
    "groups": [
      "Developing countries",
      "America",
      "South America"
    ]
  },
  "437": {
    "name": "Colombia",
    "groups": [
      "Developing countries",
      "America",
      "South America",
      "Upper-middle income countries",
      "Middle income countries"
    ]
  },
  "440": {
    "name": "Ecuador",
    "groups": [
      "Developing countries",
      "America",
      "South America",
      "Upper-middle income countries",
      "Middle income countries"
    ]
  },
  "446": {
    "name": "Guyana",
    "groups": [
      "Developing countries",
      "America",
      "South America",
      "Upper-middle income countries",
      "Middle income countries"
    ]
  },
  "451": {
    "name": "Paraguay",
    "groups": [
      "Developing countries",
      "America",
      "South America",
      "Upper-middle income countries",
      "Middle income countries"
    ]
  },
  "454": {
    "name": "Peru",
    "groups": [
      "Developing countries",
      "America",
      "South America",
      "Upper-middle income countries",
      "Middle income countries"
    ]
  },
  "457": {
    "name": "Suriname",
    "groups": [
      "Developing countries",
      "America",
      "South America",
      "Upper-middle income countries",
      "Middle income countries"
    ]
  },
  "460": {
    "name": "Uruguay",
    "groups": [
      "Developing countries",
      "America",
      "South America"
    ]
  },
  "463": {
    "name": "Venezuela",
    "groups": [
      "Developing countries",
      "America",
      "South America",
      "Upper-middle income countries",
      "Middle income countries",
      "Fragile and conflict-affected countries"
    ]
  },
  "489": {
    "name": "South America, unspecified",
    "groups": [
      "Developing countries",
      "America",
      "South America"
    ]
  },
  "498": {
    "name": "America, unspecified",
    "groups": [
      "Developing countries",
      "America"
    ]
  },
  "530": {
    "name": "Bahrain",
    "groups": [
      "Developing countries",
      "Asia",
      "Middle East"
    ]
  },
  "540": {
    "name": "Iran",
    "groups": [
      "Developing countries",
      "Asia",
      "Middle East",
      "Lower-middle income countries",
      "Middle income countries",
      "Fragile and conflict-affected countries"
    ]
  },
  "543": {
    "name": "Iraq",
    "groups": [
      "Developing countries",
      "Asia",
      "Middle East",
      "Upper-middle income countries",
      "Middle income countries",
      "Fragile and conflict-affected countries"
    ]
  },
  "546": {
    "name": "Israel",
    "groups": [
      "Developing countries",
      "Asia",
      "Middle East"
    ]
  },
  "549": {
    "name": "Jordan",
    "groups": [
      "Developing countries",
      "Asia",
      "Middle East",
      "Upper-middle income countries",
      "Middle income countries"
    ]
  },
  "550": {
    "name": "West Bank and Gaza Strip",
    "groups": [
      "Developing countries",
      "Asia",
      "Middle East",
      "Lower-middle income countries",
      "Middle income countries",
      "Fragile and conflict-affected countries"
    ]
  },
  "552": {
    "name": "Kuwait",
    "groups": [
      "Developing countries",
      "Asia",
      "Middle East"
    ]
  },
  "555": {
    "name": "Lebanon",
    "groups": [
      "Developing countries",
      "Asia",
      "Middle East",
      "Upper-middle income countries",
      "Middle income countries"
    ]
  },
  "558": {
    "name": "Oman",
    "groups": [
      "Developing countries",
      "Asia",
      "Middle East"
    ]
  },
  "561": {
    "name": "Qatar",
    "groups": [
      "Developing countries",
      "Asia",
      "Middle East"
    ]
  },
  "566": {
    "name": "Saudi Arabia",
    "groups": [
      "Developing countries",
      "Asia",
      "Middle East"
    ]
  },
  "573": {
    "name": "Syrian Arab Republic",
    "groups": [
      "Developing countries",
      "Asia",
      "Middle East",
      "Low income countries",
      "Fragile and conflict-affected countries"
    ]
  },
  "576": {
    "name": "United Arab Emirates",
    "groups": [
      "Developing countries",
      "Asia",
      "Middle East"
    ]
  },
  "580": {
    "name": "Yemen",
    "groups": [
      "Developing countries",
      "Asia",
      "Middle East",
      "Least developed countries",
      "Fragile and conflict-affected countries"
    ]
  },
  "589": {
    "name": "Middle East, unspecified",
    "groups": [
      "Developing countries",
      "Asia",
      "Middle East"
    ]
  },
  "610": {
    "name": "Armenia",
    "groups": [
      "Developing countries",
      "Asia",
      "Southern and Central Asia",
      "Upper-middle income countries",
      "Middle income countries"
    ]
  },
  "611": {
    "name": "Azerbaijan",
    "groups": [
      "Developing countries",
      "Asia",
      "Southern and Central Asia",
      "Upper-middle income countries",
      "Middle income countries"
    ]
  },
  "612": {
    "name": "Georgia",
    "groups": [
      "Developing countries",
      "Asia",
      "Southern and Central Asia",
      "Upper-middle income countries",
      "Middle income countries"
    ]
  },
  "613": {
    "name": "Kazakhstan",
    "groups": [
      "Developing countries",
      "Asia",
      "Southern and Central Asia",
      "Upper-middle income countries",
      "Middle income countries"
    ]
  },
  "614": {
    "name": "Kyrgyzstan",
    "groups": [
      "Developing countries",
      "Asia",
      "Southern and Central Asia",
      "Lower-middle income countries",
      "Middle income countries"
    ]
  },
  "615": {
    "name": "Tajikistan",
    "groups": [
      "Developing countries",
      "Asia",
      "Southern and Central Asia",
      "Lower-middle income countries",
      "Middle income countries",
      "Fragile and conflict-affected countries"
    ]
  },
  "616": {
    "name": "Turkmenistan",
    "groups": [
      "Developing countries",
      "Asia",
      "Southern and Central Asia",
      "Upper-middle income countries",
      "Middle income countries",
      "Fragile and conflict-affected countries"
    ]
  },
  "617": {
    "name": "Uzbekistan",
    "groups": [
      "Developing countries",
      "Asia",
      "Southern and Central Asia",
      "Lower-middle income countries",
      "Middle income countries"
    ]
  },
  "619": {
    "name": "Central Asia, unspecified",
    "groups": [
      "Developing countries",
      "Asia",
      "Southern and Central Asia"
    ]
  },
  "625": {
    "name": "Afghanistan",
    "groups": [
      "Developing countries",
      "Asia",
      "Southern and Central Asia",
      "Least developed countries",
      "Fragile and conflict-affected countries"
    ]
  },
  "630": {
    "name": "Bhutan",
    "groups": [
      "Developing countries",
      "Asia",
      "Southern and Central Asia",
      "Least developed countries"
    ]
  },
  "635": {
    "name": "Myanmar",
    "groups": [
      "Developing countries",
      "Asia",
      "Southern and Central Asia",
      "Least developed countries",
      "Fragile and conflict-affected countries"
    ]
  },
  "640": {
    "name": "Sri Lanka",
    "groups": [
      "Developing countries",
      "Asia",
      "Southern and Central Asia",
      "Lower-middle income countries",
      "Middle income countries"
    ]
  },
  "645": {
    "name": "India",
    "groups": [
      "Developing countries",
      "Asia",
      "Southern and Central Asia",
      "Lower-middle income countries",
      "Middle income countries"
    ]
  },
  "655": {
    "name": "Maldives",
    "groups": [
      "Developing countries",
      "Asia",
      "Southern and Central Asia",
      "Upper-middle income countries",
      "Middle income countries"
    ]
  },
  "660": {
    "name": "Nepal",
    "groups": [
      "Developing countries",
      "Asia",
      "Southern and Central Asia",
      "Least developed countries"
    ]
  },
  "665": {
    "name": "Pakistan",
    "groups": [
      "Developing countries",
      "Asia",
      "Southern and Central Asia",
      "Lower-middle income countries",
      "Middle income countries",
      "Fragile and conflict-affected countries"
    ]
  },
  "666": {
    "name": "Bangladesh",
    "groups": [
      "Developing countries",
      "Asia",
      "Southern and Central Asia",
      "Least developed countries",
      "Fragile and conflict-affected countries"
    ]
  },
  "689": {
    "name": "Southern and Central Asia, unspecified",
    "groups": [
      "Developing countries",
      "Asia",
      "Southern and Central Asia"
    ]
  },
  "725": {
    "name": "Brunei Darussalam",
    "groups": [
      "Developing countries",
      "Asia",
      "Far East Asia"
    ]
  },
  "728": {
    "name": "Cambodia",
    "groups": [
      "Developing countries",
      "Asia",
      "Far East Asia",
      "Least developed countries",
      "Fragile and conflict-affected countries"
    ]
  },
  "730": {
    "name": "China (People's Republic of)",
    "groups": [
      "Developing countries",
      "Asia",
      "Far East Asia",
      "Upper-middle income countries",
      "Middle income countries"
    ]
  },
  "738": {
    "name": "Indonesia",
    "groups": [
      "Developing countries",
      "Asia",
      "Far East Asia",
      "Lower-middle income countries",
      "Middle income countries"
    ]
  },
  "740": {
    "name": "Democratic People's Republic of Korea",
    "groups": [
      "Developing countries",
      "Asia",
      "Far East Asia",
      "Low income countries",
      "Fragile and conflict-affected countries"
    ]
  },
  "745": {
    "name": "Lao People's Democratic Republic",
    "groups": [
      "Developing countries",
      "Asia",
      "Far East Asia",
      "Least developed countries",
      "Fragile and conflict-affected countries"
    ]
  },
  "748": {
    "name": "Macau (China)",
    "groups": [
      "Developing countries",
      "Asia",
      "Far East Asia"
    ]
  },
  "751": {
    "name": "Malaysia",
    "groups": [
      "Developing countries",
      "Asia",
      "Far East Asia",
      "Upper-middle income countries",
      "Middle income countries"
    ]
  },
  "753": {
    "name": "Mongolia",
    "groups": [
      "Developing countries",
      "Asia",
      "Far East Asia",
      "Lower-middle income countries",
      "Middle income countries"
    ]
  },
  "755": {
    "name": "Philippines",
    "groups": [
      "Developing countries",
      "Asia",
      "Far East Asia",
      "Lower-middle income countries",
      "Middle income countries"
    ]
  },
  "764": {
    "name": "Thailand",
    "groups": [
      "Developing countries",
      "Asia",
      "Far East Asia",
      "Upper-middle income countries",
      "Middle income countries"
    ]
  },
  "765": {
    "name": "Timor-Leste",
    "groups": [
      "Developing countries",
      "Asia",
      "Far East Asia",
      "Least developed countries",
      "Fragile and conflict-affected countries"
    ]
  },
  "769": {
    "name": "Viet Nam",
    "groups": [
      "Developing countries",
      "Asia",
      "Far East Asia",
      "Lower-middle income countries",
      "Middle income countries"
    ]
  },
  "789": {
    "name": "Far East Asia, unspecified",
    "groups": [
      "Developing countries",
      "Asia",
      "Far East Asia"
    ]
  },
  "798": {
    "name": "Asia, unspecified",
    "groups": [
      "Developing countries",
      "Asia"
    ]
  },
  "831": {
    "name": "Cook Islands",
    "groups": [
      "Developing countries",
      "Oceania",
      "Polynesia"
    ]
  },
  "832": {
    "name": "Fiji",
    "groups": [
      "Developing countries",
      "Oceania",
      "Melanesia",
      "Upper-middle income countries",
      "Middle income countries"
    ]
  },
  "836": {
    "name": "Kiribati",
    "groups": [
      "Developing countries",
      "Oceania",
      "Micronesia",
      "Least developed countries"
    ]
  },
  "840": {
    "name": "French Polynesia",
    "groups": [
      "Developing countries",
      "Oceania",
      "Polynesia"
    ]
  },
  "845": {
    "name": "Nauru",
    "groups": [
      "Developing countries",
      "Oceania",
      "Micronesia",
      "Upper-middle income countries",
      "Middle income countries"
    ]
  },
  "850": {
    "name": "New Caledonia",
    "groups": [
      "Developing countries",
      "Oceania",
      "Melanesia"
    ]
  },
  "854": {
    "name": "Vanuatu",
    "groups": [
      "Developing countries",
      "Oceania",
      "Melanesia",
      "Lower-middle income countries",
      "Middle income countries"
    ]
  },
  "856": {
    "name": "Niue",
    "groups": [
      "Developing countries",
      "Oceania",
      "Polynesia",
      "Upper-middle income countries",
      "Middle income countries"
    ]
  },
  "858": {
    "name": "Northern Mariana Islands",
    "groups": [
      "Developing countries",
      "Oceania",
      "Micronesia"
    ]
  },
  "859": {
    "name": "Marshall Islands",
    "groups": [
      "Developing countries",
      "Oceania",
      "Micronesia",
      "Upper-middle income countries",
      "Middle income countries"
    ]
  },
  "860": {
    "name": "Micronesia",
    "groups": [
      "Developing countries",
      "Oceania",
      "Micronesia",
      "Lower-middle income countries",
      "Middle income countries"
    ]
  },
  "861": {
    "name": "Palau",
    "groups": [
      "Developing countries",
      "Oceania",
      "Micronesia",
      "Upper-middle income countries",
      "Middle income countries"
    ]
  },
  "862": {
    "name": "Papua New Guinea",
    "groups": [
      "Developing countries",
      "Oceania",
      "Melanesia",
      "Lower-middle income countries",
      "Middle income countries",
      "Fragile and conflict-affected countries"
    ]
  },
  "866": {
    "name": "Solomon Islands",
    "groups": [
      "Developing countries",
      "Oceania",
      "Melanesia",
      "Least developed countries",
      "Fragile and conflict-affected countries"
    ]
  },
  "868": {
    "name": "Tokelau",
    "groups": [
      "Developing countries",
      "Oceania",
      "Polynesia",
      "Lower-middle income countries",
      "Middle income countries"
    ]
  },
  "870": {
    "name": "Tonga",
    "groups": [
      "Developing countries",
      "Oceania",
      "Polynesia",
      "Upper-middle income countries",
      "Middle income countries"
    ]
  },
  "872": {
    "name": "Tuvalu",
    "groups": [
      "Developing countries",
      "Oceania",
      "Polynesia",
      "Least developed countries"
    ]
  },
  "876": {
    "name": "Wallis and Futuna",
    "groups": [
      "Developing countries",
      "Oceania",
      "Polynesia",
      "Upper-middle income countries",
      "Middle income countries"
    ]
  },
  "880": {
    "name": "Samoa",
    "groups": [
      "Developing countries",
      "Oceania",
      "Polynesia",
      "Lower-middle income countries",
      "Middle income countries"
    ]
  },
  "889": {
    "name": "Oceania, unspecified",
    "groups": [
      "Developing countries",
      "Oceania"
    ]
  },
  "1027": {
    "name": "Eastern Africa, unspecified",
    "groups": [
      "Developing countries",
      "Africa",
      "Sub-Saharan Africa",
      "Eastern Africa"
    ]
  },
  "1029": {
    "name": "Southern Africa, unspecified",
    "groups": [
      "Developing countries",
      "Africa",
      "Sub-Saharan Africa",
      "Southern Africa"
    ]
  },
  "1030": {
    "name": "Western Africa, unspecified",
    "groups": [
      "Developing countries",
      "Africa",
      "Sub-Saharan Africa",
      "Western Africa"
    ]
  },
  "1031": {
    "name": "Caribbean, unspecified",
    "groups": [
      "Developing countries",
      "America",
      "Central America and the Caribbean",
      "Caribbean"
    ]
  },
  "1032": {
    "name": "Central America, unspecified",
    "groups": [
      "Developing countries",
      "America",
      "Central America and the Caribbean",
      "Central America"
    ]
  },
  "6790": {
    "name": "Southern Asia, unspecified",
    "groups": [
      "Developing countries",
      "Asia",
      "Southern and Central Asia"
    ]
  },
  "8600": {
    "name": "Micronesia, unspecified",
    "groups": [
      "Developing countries",
      "Oceania",
      "Micronesia"
    ]
  },
  "9998": {
    "name": "Developing countries, unspecified",
    "groups": [
      "Developing countries",
      "Developing countries"
    ]
  },
  "10280": {
    "name": "Middle Africa, unspecified",
    "groups": [
      "Developing countries",
      "Africa",
      "Sub-Saharan Africa",
      "Middle Africa"
    ]
  },
  "10330": {
    "name": "Melanesia, unspecified",
    "groups": [
      "Developing countries",
      "Oceania",
      "Melanesia"
    ]
  },
  "10350": {
    "name": "Polynesia, unspecified",
    "groups": [
      "Developing countries",
      "Oceania",
      "Polynesia"
    ]
  }
}